cilpy/runner.py
cilpy-0.0.2.dist-info/licenses/LICENSE
cilpy-0.0.2.dist-info/METADATA
cilpy-0.0.2.dist-info/WHEEL
cilpy-0.0.2.dist-info/top_level.txt
cilpy-0.0.2.dist-info/RECORD
