Metadata-Version: 2.4
Name: cilpy
Version: 0.0.2
Summary: A computational intelligence library for Python.
Author-email: Willie Loftie-Eaton <willieloea@gmail.com>
License-Expression: MIT
Project-URL: Homepage, https://github.com/willieloea/cilpy
Project-URL: Issues, https://github.com/willieloea/cilpy/issues
Project-URL: Repository, https://github.com/willieloea/cilpy
Requires-Python: >=3.8
License-File: LICENSE
Requires-Dist: matplotlib>=3.10.7
Requires-Dist: numpy>=2.3.4
Requires-Dist: pandas>=2.3.3
Requires-Dist: pytest>=8.4.2
Dynamic: license-file
